README.md
setup.py
smart_crypt/__init__.py
smart_crypt/crypt.py
smart_crypt/utils.py
smart_manage_crypt.egg-info/PKG-INFO
smart_manage_crypt.egg-info/SOURCES.txt
smart_manage_crypt.egg-info/dependency_links.txt
smart_manage_crypt.egg-info/requires.txt
smart_manage_crypt.egg-info/top_level.txt