Metadata-Version: 2.1
Name: smart-manage-crypt
Version: 0.0.2b0
Requires-Python: >=3.10
Requires-Dist: pycryptodome==3.20.0
